youtubedlapi_server_infusiblecoder/__init__.py
youtubedlapi_server_infusiblecoder/__main__.py
youtubedlapi_server_infusiblecoder/app.py
youtubedlapi_server_infusiblecoder/bili.py
youtubedlapi_server_infusiblecoder/celery_app_test.py
youtubedlapi_server_infusiblecoder/celery_config.py
youtubedlapi_server_infusiblecoder/fastapi_test.py
youtubedlapi_server_infusiblecoder/old_copy.py
youtubedlapi_server_infusiblecoder/orignal_app.py
youtubedlapi_server_infusiblecoder/server.py
youtubedlapi_server_infusiblecoder/version.py
youtubedlapi_server_infusiblecoder-3.7.9.dist-info/AUTHORS.md
youtubedlapi_server_infusiblecoder-3.7.9.dist-info/LICENSE.md
youtubedlapi_server_infusiblecoder-3.7.9.dist-info/METADATA
youtubedlapi_server_infusiblecoder-3.7.9.dist-info/WHEEL
youtubedlapi_server_infusiblecoder-3.7.9.dist-info/entry_points.txt
youtubedlapi_server_infusiblecoder-3.7.9.dist-info/top_level.txt
youtubedlapi_server_infusiblecoder-3.7.9.dist-info/RECORD
