Metadata-Version: 2.1
Name: youtubedlapi_server_infusiblecoder
Version: 3.7.9
Summary: An API server based on yt-dlp
Home-page: https://github.com/syedusama5556/youtubedlapi-server-infusiblecoder
Author: Syed Usama Ahmad
Author-email: syedusama5556@gmail.com
Classifier: Topic :: Multimedia :: Video
Classifier: Topic :: Internet :: WWW/HTTP :: WSGI
Classifier: Development Status :: 3 - Alpha
Classifier: Environment :: Console
Classifier: License :: Public Domain
Classifier: Programming Language :: Python :: 2.7
Classifier: Programming Language :: Python :: 3
Classifier: Programming Language :: Python :: 3.3
License-File: LICENSE.md
License-File: AUTHORS.md
Requires-Dist: fastapi
Requires-Dist: Flask (>=3.0.3)
Requires-Dist: yt-dlp (>=2024.4.9)
Requires-Dist: Flask-Caching
Requires-Dist: flask-caching
Requires-Dist: gevent
Requires-Dist: uvicorn[standard]
Requires-Dist: bilix
Requires-Dist: httpx
Requires-Dist: asgiref
Requires-Dist: gunicorn
Requires-Dist: redis
Requires-Dist: celery
